extra/fnaffle.py
extra/make_isbn_ranges.py
fna/__init__.py
util/__init__.py
util/checksum.py
util/checksum_test.py
util/config.py
util/config_test.py
util/docsplit.py
util/docsplit_test.py
util/duration.py
util/duration_test.py
util/error.py
util/escape.py
util/escape_test.py
util/fearmat.py
util/fearmat_test.py
util/io.py
util/io_test.py
util/multimap.py
util/multimap_test.py
util/pytestutil.py
util/registry.py
util/registry_test.py
util/repr.py
util/repr_test.py
util/sqlite.py
util/sqlite_test.py
util/typecheck.py
util/typecheck_test.py
vlju/__init__.py
vlju/testutil.py
vlju/vlju_test.py
vlju/types/__init__.py
vlju/types/all.py
vlju/types/doi/__init__.py
vlju/types/doi/doi_test.py
vlju/types/doi/org.py
vlju/types/ean/__init__.py
vlju/types/ean/ean_test.py
vlju/types/ean/isbn.py
vlju/types/ean/isbn_ranges.py
vlju/types/ean/isbn_test.py
vlju/types/ean/ismn.py
vlju/types/ean/ismn_test.py
vlju/types/ean/issn.py
vlju/types/ean/issn_test.py
vlju/types/file/__init__.py
vlju/types/file/file_test.py
vlju/types/info/__init__.py
vlju/types/info/info_test.py
vlju/types/info/kinds.py
vlju/types/lccn/__init__.py
vlju/types/lccn/lccn_test.py
vlju/types/site/__init__.py
vlju/types/site/site_test.py
vlju/types/site/sites_test.py
vlju/types/timestamp/__init__.py
vlju/types/timestamp/timestamp_test.py
vlju/types/uri/__init__.py
vlju/types/uri/uri_test.py
vlju/types/url/__init__.py
vlju/types/url/url_test.py
vlju/types/urn/__init__.py
vlju/types/urn/kinds.py
vlju/types/urn/urn_test.py
vljum/__init__.py
vljum/m.py
vljum/m_test.py
vljum/runner.py
vljum/runner_test.py
vljumap/__init__.py
vljumap/enc.py
vljumap/enc_test.py
vljumap/factory.py
vljumap/factory_test.py
vljumap/vljumap_test.py
file_name_attributes-0.2.4.dist-info/LICENSE
file_name_attributes-0.2.4.dist-info/METADATA
file_name_attributes-0.2.4.dist-info/WHEEL
file_name_attributes-0.2.4.dist-info/entry_points.txt
file_name_attributes-0.2.4.dist-info/top_level.txt
file_name_attributes-0.2.4.dist-info/RECORD
