Metadata-Version: 2.1
Name: file-name-attributes
Version: 0.2.4
Summary: Manage key/value metadata in file names.
License: MIT License
Project-URL: repository, https://codeberg.org/datatravelandexperiments/fna
Classifier: Development Status :: 4 - Beta
Classifier: Environment :: Console
Classifier: Intended Audience :: End Users/Desktop
Classifier: License :: OSI Approved :: MIT License
Classifier: Natural Language :: English
Classifier: Operating System :: POSIX
Classifier: Programming Language :: Python :: 3.11
Classifier: Topic :: Utilities
Classifier: Typing :: Typed
Requires-Python: >=3.11
License-File: LICENSE
